{
  "connections": [
    {
      "class": "federated",
      "server": "",
      "database": null,
      "schema": "",
      "username": null,
      "port": null,
      "authentication": null,
      "table_name": "Custom SQL Query",
      "sql_queries": []
    },
    {
      "class": "federated",
      "server": "",
      "database": null,
      "schema": "",
      "username": null,
      "port": null,
      "authentication": null,
      "table_name": "Custom SQL Query1",
      "sql_queries": []
    },
    {
      "class": "federated",
      "server": null,
      "database": null,
      "schema": null,
      "username": null,
      "port": null,
      "authentication": null,
      "table_name": "Sheet1$",
      "sql_queries": []
    },
    {
      "class": "federated",
      "server": null,
      "database": null,
      "schema": null,
      "username": null,
      "port": null,
      "authentication": null,
      "table_name": "Sheet1$",
      "sql_queries": [
        {
          "name": "Custom SQL Query",
          "type": "text",
          "sql_query": "select 'System' Tab_module,asup_month as asup_date,dt,count(*) as serial_count from\n(select 'System' PUAT_Module,substring(a.asup_id,1,8) as asup_month,a.dt,sys_serial_no from dlh_nsec.objdb.\"system\" a \njoin dlh_nsec.objdb.asup b on a.asup_id = b.asup_id \nwhere a.dt >>= '20240301' and a.dt <<= '20240530'\nand b.dt >>= '20240301' and b.dt <<= '20240530'\nand lower(b.asup_subject) like '%weekly%'\nand upper(b.asup_type) = 'DOT-REGULAR'\nand a.asup_id='2022050100000239'\nand upper(cfo_node_state) not in ('TAKEOVER','DOWN'))\ngroup by asup_month,dt"
        },
        {
          "name": "Custom SQL Query1",
          "type": "text",
          "sql_query": "select fd.*,to_char(fiscal_date,'yyyymmdd') as ft from fiscaltime fd"
        },
        {
          "name": "Custom SQL Query2",
          "type": "text",
          "sql_query": "select CASE OBJ_SMF_TABLES WHEN 'cmstatsweeklydb_wafl_count' THEN 'CMS Stats wafl Count'\r\nWHEN 'cmstatsweeklydb_wafl_sys' THEN 'CMS Stats wafl Sys'\r\nWHEN 'cmstatsweeklydb_volume_count' THEN 'CMS Stats Volume Count'\r\nWHEN 'cmstatsweeklydb_volume_sys' THEN 'CMS Stats Volume Sys'\r\nWHEN 'Snaplock_volume' THEN 'Snaplock Volume'\r\nWHEN 'Igroup' THEN 'igroup'\r\nWHEN 'Snapmirror_policy' THEN 'snapmirror policy'\r\nWHEN 'Snapmirror_destination' THEN 'SnapMirror Destination' \r\nWHEN 'Volume' THEN 'SMFDBV2 Volume'\r\nELSE OBJ_SMF_TABLES END AS OBJ_SMF_TABLES,AVG_DATA\r\n from dlh_reporting_s3.asuprep.puat_avg_table_counts"
        },
        {
          "name": "Custom SQL Query",
          "type": "text",
          "sql_query": "select 'System' Tab_module,asup_month as asup_date,dt,count(*) as serial_count from\n(select 'System' PUAT_Module,substring(a.asup_id,1,8) as asup_month,a.dt,sys_serial_no from dlh_nsec.objdb.\"system\" a \njoin dlh_nsec.objdb.asup b on a.asup_id = b.asup_id \nwhere a.dt >>= '20240301' and a.dt <<= '20240530'\nand b.dt >>= '20240301' and b.dt <<= '20240530'\nand lower(b.asup_subject) like '%weekly%'\nand upper(b.asup_type) = 'DOT-REGULAR'\nand a.asup_id='2022050100000239'\nand upper(cfo_node_state) not in ('TAKEOVER','DOWN'))\ngroup by asup_month,dt"
        },
        {
          "name": "Custom SQL Query1",
          "type": "text",
          "sql_query": "select fd.*,to_char(fiscal_date,'yyyymmdd') as ft from fiscaltime fd"
        },
        {
          "name": "Custom SQL Query2",
          "type": "text",
          "sql_query": "select CASE OBJ_SMF_TABLES WHEN 'cmstatsweeklydb_wafl_count' THEN 'CMS Stats wafl Count'\r\nWHEN 'cmstatsweeklydb_wafl_sys' THEN 'CMS Stats wafl Sys'\r\nWHEN 'cmstatsweeklydb_volume_count' THEN 'CMS Stats Volume Count'\r\nWHEN 'cmstatsweeklydb_volume_sys' THEN 'CMS Stats Volume Sys'\r\nWHEN 'Snaplock_volume' THEN 'Snaplock Volume'\r\nWHEN 'Igroup' THEN 'igroup'\r\nWHEN 'Snapmirror_policy' THEN 'snapmirror policy'\r\nWHEN 'Snapmirror_destination' THEN 'SnapMirror Destination' \r\nWHEN 'Volume' THEN 'SMFDBV2 Volume'\r\nELSE OBJ_SMF_TABLES END AS OBJ_SMF_TABLES,AVG_DATA\r\n from dlh_reporting_s3.asuprep.puat_avg_table_counts"
        }
      ]
    },
    {
      "class": "federated",
      "server": null,
      "database": null,
      "schema": null,
      "username": null,
      "port": null,
      "authentication": null,
      "table_name": "Sheet1$",
      "sql_queries": [
        {
          "name": "Custom SQL Query",
          "type": "text",
          "sql_query": "select * from dlh_reporting_s3.asuprep.PUAT_dremio_dashboard_table_final\r\nwhere puat_module='hussain'"
        },
        {
          "name": "Custom SQL Query1",
          "type": "text",
          "sql_query": "select fd.*,to_char(fiscal_date,'yyyymmdd') as ft from fiscaltime fd\r\nwhere to_char(fiscal_date,'DY') in ('SAT','SUN')"
        },
        {
          "name": "Custom SQL Query2",
          "type": "text",
          "sql_query": "select CASE OBJ_SMF_TABLES WHEN 'cmstatsweeklydb_wafl_count' THEN 'CMS Stats wafl Count'\r\nWHEN 'cmstatsweeklydb_wafl_sys' THEN 'CMS Stats wafl Sys'\r\nWHEN 'cmstatsweeklydb_volume_count' THEN 'CMS Stats Volume Count'\r\nWHEN 'cmstatsweeklydb_volume_sys' THEN 'CMS Stats Volume Sys'\r\nWHEN 'Snaplock_volume' THEN 'Snaplock Volume'\r\nWHEN 'Igroup' THEN 'igroup'\r\nWHEN 'Snapmirror_policy' THEN 'snapmirror policy'\r\nWHEN 'Snapmirror_destination' THEN 'SnapMirror Destination' \r\nWHEN 'volume' THEN 'SMFDBV2 Volume'\r\nWhen 'volume_move_show_table' THEN 'Volume Move Show'\r\nELSE OBJ_SMF_TABLES END AS OBJ_SMF_TABLES,AVG_DATA,Max_data\r\n from dlh_reporting_s3.asuprep.PUAT_dashboard_avg_table"
        },
        {
          "name": "Custom SQL Query",
          "type": "text",
          "sql_query": "select * from dlh_reporting_s3.asuprep.PUAT_dremio_dashboard_table_final\r\nwhere puat_module='hussain'"
        },
        {
          "name": "Custom SQL Query1",
          "type": "text",
          "sql_query": "select fd.*,to_char(fiscal_date,'yyyymmdd') as ft from fiscaltime fd\r\nwhere to_char(fiscal_date,'DY') in ('SAT','SUN')"
        },
        {
          "name": "Custom SQL Query2",
          "type": "text",
          "sql_query": "select CASE OBJ_SMF_TABLES WHEN 'cmstatsweeklydb_wafl_count' THEN 'CMS Stats wafl Count'\r\nWHEN 'cmstatsweeklydb_wafl_sys' THEN 'CMS Stats wafl Sys'\r\nWHEN 'cmstatsweeklydb_volume_count' THEN 'CMS Stats Volume Count'\r\nWHEN 'cmstatsweeklydb_volume_sys' THEN 'CMS Stats Volume Sys'\r\nWHEN 'Snaplock_volume' THEN 'Snaplock Volume'\r\nWHEN 'Igroup' THEN 'igroup'\r\nWHEN 'Snapmirror_policy' THEN 'snapmirror policy'\r\nWHEN 'Snapmirror_destination' THEN 'SnapMirror Destination' \r\nWHEN 'volume' THEN 'SMFDBV2 Volume'\r\nWhen 'volume_move_show_table' THEN 'Volume Move Show'\r\nELSE OBJ_SMF_TABLES END AS OBJ_SMF_TABLES,AVG_DATA,Max_data\r\n from dlh_reporting_s3.asuprep.PUAT_dashboard_avg_table"
        }
      ]
    },
    {
      "class": "federated",
      "server": null,
      "database": null,
      "schema": null,
      "username": null,
      "port": null,
      "authentication": null,
      "table_name": "Custom SQL Query",
      "sql_queries": []
    },
    {
      "class": "federated",
      "server": null,
      "database": null,
      "schema": null,
      "username": null,
      "port": null,
      "authentication": null,
      "table_name": "Custom SQL Query",
      "sql_queries": [
        {
          "name": "Custom SQL Query",
          "type": "text",
          "sql_query": "select 'System' Tab_module,asup_month as asup_date,dt,count(*) as serial_count from\n(select 'System' PUAT_Module,substring(a.asup_id,1,8) as asup_month,a.dt,sys_serial_no from dlh_nsec.objdb.\"system\" a \njoin dlh_nsec.objdb.asup b on a.asup_id = b.asup_id \nwhere a.dt >>= '20240301' and a.dt <<= '20240530'\nand b.dt >>= '20240301' and b.dt <<= '20240530'\nand lower(b.asup_subject) like '%weekly%'\nand upper(b.asup_type) = 'DOT-REGULAR'\nand a.asup_id='2022050100000239'\nand upper(cfo_node_state) not in ('TAKEOVER','DOWN'))\ngroup by asup_month,dt"
        },
        {
          "name": "Custom SQL Query1",
          "type": "text",
          "sql_query": "select fd.*,to_char(fiscal_date,'yyyymmdd') as ft from fiscaltime fd"
        },
        {
          "name": "Custom SQL Query2",
          "type": "text",
          "sql_query": "select CASE OBJ_SMF_TABLES WHEN 'cmstatsweeklydb_wafl_count' THEN 'CMS Stats wafl Count'\r\nWHEN 'cmstatsweeklydb_wafl_sys' THEN 'CMS Stats wafl Sys'\r\nWHEN 'cmstatsweeklydb_volume_count' THEN 'CMS Stats Volume Count'\r\nWHEN 'cmstatsweeklydb_volume_sys' THEN 'CMS Stats Volume Sys'\r\nWHEN 'Snaplock_volume' THEN 'Snaplock Volume'\r\nWHEN 'Igroup' THEN 'igroup'\r\nWHEN 'Snapmirror_policy' THEN 'snapmirror policy'\r\nWHEN 'Snapmirror_destination' THEN 'SnapMirror Destination' \r\nWHEN 'Volume' THEN 'SMFDBV2 Volume'\r\nELSE OBJ_SMF_TABLES END AS OBJ_SMF_TABLES,AVG_DATA\r\n from dlh_reporting_s3.asuprep.puat_avg_table_counts"
        },
        {
          "name": "Custom SQL Query",
          "type": "text",
          "sql_query": "select 'System' Tab_module,asup_month as asup_date,dt,count(*) as serial_count from\n(select 'System' PUAT_Module,substring(a.asup_id,1,8) as asup_month,a.dt,sys_serial_no from dlh_nsec.objdb.\"system\" a \njoin dlh_nsec.objdb.asup b on a.asup_id = b.asup_id \nwhere a.dt >>= '20240301' and a.dt <<= '20240530'\nand b.dt >>= '20240301' and b.dt <<= '20240530'\nand lower(b.asup_subject) like '%weekly%'\nand upper(b.asup_type) = 'DOT-REGULAR'\nand a.asup_id='2022050100000239'\nand upper(cfo_node_state) not in ('TAKEOVER','DOWN'))\ngroup by asup_month,dt"
        },
        {
          "name": "Custom SQL Query1",
          "type": "text",
          "sql_query": "select fd.*,to_char(fiscal_date,'yyyymmdd') as ft from fiscaltime fd"
        },
        {
          "name": "Custom SQL Query2",
          "type": "text",
          "sql_query": "select CASE OBJ_SMF_TABLES WHEN 'cmstatsweeklydb_wafl_count' THEN 'CMS Stats wafl Count'\r\nWHEN 'cmstatsweeklydb_wafl_sys' THEN 'CMS Stats wafl Sys'\r\nWHEN 'cmstatsweeklydb_volume_count' THEN 'CMS Stats Volume Count'\r\nWHEN 'cmstatsweeklydb_volume_sys' THEN 'CMS Stats Volume Sys'\r\nWHEN 'Snaplock_volume' THEN 'Snaplock Volume'\r\nWHEN 'Igroup' THEN 'igroup'\r\nWHEN 'Snapmirror_policy' THEN 'snapmirror policy'\r\nWHEN 'Snapmirror_destination' THEN 'SnapMirror Destination' \r\nWHEN 'Volume' THEN 'SMFDBV2 Volume'\r\nELSE OBJ_SMF_TABLES END AS OBJ_SMF_TABLES,AVG_DATA\r\n from dlh_reporting_s3.asuprep.puat_avg_table_counts"
        }
      ]
    },
    {
      "class": "federated",
      "server": null,
      "database": null,
      "schema": null,
      "username": null,
      "port": null,
      "authentication": null,
      "table_name": "Custom SQL Query",
      "sql_queries": [
        {
          "name": "Custom SQL Query",
          "type": "text",
          "sql_query": "select * from dlh_reporting_s3.asuprep.PUAT_dremio_dashboard_table_final\r\nwhere puat_module='hussain'"
        },
        {
          "name": "Custom SQL Query1",
          "type": "text",
          "sql_query": "select fd.*,to_char(fiscal_date,'yyyymmdd') as ft from fiscaltime fd\r\nwhere to_char(fiscal_date,'DY') in ('SAT','SUN')"
        },
        {
          "name": "Custom SQL Query2",
          "type": "text",
          "sql_query": "select CASE OBJ_SMF_TABLES WHEN 'cmstatsweeklydb_wafl_count' THEN 'CMS Stats wafl Count'\r\nWHEN 'cmstatsweeklydb_wafl_sys' THEN 'CMS Stats wafl Sys'\r\nWHEN 'cmstatsweeklydb_volume_count' THEN 'CMS Stats Volume Count'\r\nWHEN 'cmstatsweeklydb_volume_sys' THEN 'CMS Stats Volume Sys'\r\nWHEN 'Snaplock_volume' THEN 'Snaplock Volume'\r\nWHEN 'Igroup' THEN 'igroup'\r\nWHEN 'Snapmirror_policy' THEN 'snapmirror policy'\r\nWHEN 'Snapmirror_destination' THEN 'SnapMirror Destination' \r\nWHEN 'volume' THEN 'SMFDBV2 Volume'\r\nWhen 'volume_move_show_table' THEN 'Volume Move Show'\r\nELSE OBJ_SMF_TABLES END AS OBJ_SMF_TABLES,AVG_DATA,Max_data\r\n from dlh_reporting_s3.asuprep.PUAT_dashboard_avg_table"
        },
        {
          "name": "Custom SQL Query",
          "type": "text",
          "sql_query": "select * from dlh_reporting_s3.asuprep.PUAT_dremio_dashboard_table_final\r\nwhere puat_module='hussain'"
        },
        {
          "name": "Custom SQL Query1",
          "type": "text",
          "sql_query": "select fd.*,to_char(fiscal_date,'yyyymmdd') as ft from fiscaltime fd\r\nwhere to_char(fiscal_date,'DY') in ('SAT','SUN')"
        },
        {
          "name": "Custom SQL Query2",
          "type": "text",
          "sql_query": "select CASE OBJ_SMF_TABLES WHEN 'cmstatsweeklydb_wafl_count' THEN 'CMS Stats wafl Count'\r\nWHEN 'cmstatsweeklydb_wafl_sys' THEN 'CMS Stats wafl Sys'\r\nWHEN 'cmstatsweeklydb_volume_count' THEN 'CMS Stats Volume Count'\r\nWHEN 'cmstatsweeklydb_volume_sys' THEN 'CMS Stats Volume Sys'\r\nWHEN 'Snaplock_volume' THEN 'Snaplock Volume'\r\nWHEN 'Igroup' THEN 'igroup'\r\nWHEN 'Snapmirror_policy' THEN 'snapmirror policy'\r\nWHEN 'Snapmirror_destination' THEN 'SnapMirror Destination' \r\nWHEN 'volume' THEN 'SMFDBV2 Volume'\r\nWhen 'volume_move_show_table' THEN 'Volume Move Show'\r\nELSE OBJ_SMF_TABLES END AS OBJ_SMF_TABLES,AVG_DATA,Max_data\r\n from dlh_reporting_s3.asuprep.PUAT_dashboard_avg_table"
        }
      ]
    },
    {
      "class": "federated",
      "server": null,
      "database": null,
      "schema": null,
      "username": null,
      "port": null,
      "authentication": null,
      "table_name": "Custom SQL Query1",
      "sql_queries": []
    },
    {
      "class": "federated",
      "server": null,
      "database": null,
      "schema": null,
      "username": null,
      "port": null,
      "authentication": null,
      "table_name": "Custom SQL Query1",
      "sql_queries": [
        {
          "name": "Custom SQL Query",
          "type": "text",
          "sql_query": "select 'System' Tab_module,asup_month as asup_date,dt,count(*) as serial_count from\n(select 'System' PUAT_Module,substring(a.asup_id,1,8) as asup_month,a.dt,sys_serial_no from dlh_nsec.objdb.\"system\" a \njoin dlh_nsec.objdb.asup b on a.asup_id = b.asup_id \nwhere a.dt >>= '20240301' and a.dt <<= '20240530'\nand b.dt >>= '20240301' and b.dt <<= '20240530'\nand lower(b.asup_subject) like '%weekly%'\nand upper(b.asup_type) = 'DOT-REGULAR'\nand a.asup_id='2022050100000239'\nand upper(cfo_node_state) not in ('TAKEOVER','DOWN'))\ngroup by asup_month,dt"
        },
        {
          "name": "Custom SQL Query1",
          "type": "text",
          "sql_query": "select fd.*,to_char(fiscal_date,'yyyymmdd') as ft from fiscaltime fd"
        },
        {
          "name": "Custom SQL Query2",
          "type": "text",
          "sql_query": "select CASE OBJ_SMF_TABLES WHEN 'cmstatsweeklydb_wafl_count' THEN 'CMS Stats wafl Count'\r\nWHEN 'cmstatsweeklydb_wafl_sys' THEN 'CMS Stats wafl Sys'\r\nWHEN 'cmstatsweeklydb_volume_count' THEN 'CMS Stats Volume Count'\r\nWHEN 'cmstatsweeklydb_volume_sys' THEN 'CMS Stats Volume Sys'\r\nWHEN 'Snaplock_volume' THEN 'Snaplock Volume'\r\nWHEN 'Igroup' THEN 'igroup'\r\nWHEN 'Snapmirror_policy' THEN 'snapmirror policy'\r\nWHEN 'Snapmirror_destination' THEN 'SnapMirror Destination' \r\nWHEN 'Volume' THEN 'SMFDBV2 Volume'\r\nELSE OBJ_SMF_TABLES END AS OBJ_SMF_TABLES,AVG_DATA\r\n from dlh_reporting_s3.asuprep.puat_avg_table_counts"
        },
        {
          "name": "Custom SQL Query",
          "type": "text",
          "sql_query": "select 'System' Tab_module,asup_month as asup_date,dt,count(*) as serial_count from\n(select 'System' PUAT_Module,substring(a.asup_id,1,8) as asup_month,a.dt,sys_serial_no from dlh_nsec.objdb.\"system\" a \njoin dlh_nsec.objdb.asup b on a.asup_id = b.asup_id \nwhere a.dt >>= '20240301' and a.dt <<= '20240530'\nand b.dt >>= '20240301' and b.dt <<= '20240530'\nand lower(b.asup_subject) like '%weekly%'\nand upper(b.asup_type) = 'DOT-REGULAR'\nand a.asup_id='2022050100000239'\nand upper(cfo_node_state) not in ('TAKEOVER','DOWN'))\ngroup by asup_month,dt"
        },
        {
          "name": "Custom SQL Query1",
          "type": "text",
          "sql_query": "select fd.*,to_char(fiscal_date,'yyyymmdd') as ft from fiscaltime fd"
        },
        {
          "name": "Custom SQL Query2",
          "type": "text",
          "sql_query": "select CASE OBJ_SMF_TABLES WHEN 'cmstatsweeklydb_wafl_count' THEN 'CMS Stats wafl Count'\r\nWHEN 'cmstatsweeklydb_wafl_sys' THEN 'CMS Stats wafl Sys'\r\nWHEN 'cmstatsweeklydb_volume_count' THEN 'CMS Stats Volume Count'\r\nWHEN 'cmstatsweeklydb_volume_sys' THEN 'CMS Stats Volume Sys'\r\nWHEN 'Snaplock_volume' THEN 'Snaplock Volume'\r\nWHEN 'Igroup' THEN 'igroup'\r\nWHEN 'Snapmirror_policy' THEN 'snapmirror policy'\r\nWHEN 'Snapmirror_destination' THEN 'SnapMirror Destination' \r\nWHEN 'Volume' THEN 'SMFDBV2 Volume'\r\nELSE OBJ_SMF_TABLES END AS OBJ_SMF_TABLES,AVG_DATA\r\n from dlh_reporting_s3.asuprep.puat_avg_table_counts"
        }
      ]
    },
    {
      "class": "federated",
      "server": null,
      "database": null,
      "schema": null,
      "username": null,
      "port": null,
      "authentication": null,
      "table_name": "Custom SQL Query1",
      "sql_queries": [
        {
          "name": "Custom SQL Query",
          "type": "text",
          "sql_query": "select * from dlh_reporting_s3.asuprep.PUAT_dremio_dashboard_table_final\r\nwhere puat_module='hussain'"
        },
        {
          "name": "Custom SQL Query1",
          "type": "text",
          "sql_query": "select fd.*,to_char(fiscal_date,'yyyymmdd') as ft from fiscaltime fd\r\nwhere to_char(fiscal_date,'DY') in ('SAT','SUN')"
        },
        {
          "name": "Custom SQL Query2",
          "type": "text",
          "sql_query": "select CASE OBJ_SMF_TABLES WHEN 'cmstatsweeklydb_wafl_count' THEN 'CMS Stats wafl Count'\r\nWHEN 'cmstatsweeklydb_wafl_sys' THEN 'CMS Stats wafl Sys'\r\nWHEN 'cmstatsweeklydb_volume_count' THEN 'CMS Stats Volume Count'\r\nWHEN 'cmstatsweeklydb_volume_sys' THEN 'CMS Stats Volume Sys'\r\nWHEN 'Snaplock_volume' THEN 'Snaplock Volume'\r\nWHEN 'Igroup' THEN 'igroup'\r\nWHEN 'Snapmirror_policy' THEN 'snapmirror policy'\r\nWHEN 'Snapmirror_destination' THEN 'SnapMirror Destination' \r\nWHEN 'volume' THEN 'SMFDBV2 Volume'\r\nWhen 'volume_move_show_table' THEN 'Volume Move Show'\r\nELSE OBJ_SMF_TABLES END AS OBJ_SMF_TABLES,AVG_DATA,Max_data\r\n from dlh_reporting_s3.asuprep.PUAT_dashboard_avg_table"
        },
        {
          "name": "Custom SQL Query",
          "type": "text",
          "sql_query": "select * from dlh_reporting_s3.asuprep.PUAT_dremio_dashboard_table_final\r\nwhere puat_module='hussain'"
        },
        {
          "name": "Custom SQL Query1",
          "type": "text",
          "sql_query": "select fd.*,to_char(fiscal_date,'yyyymmdd') as ft from fiscaltime fd\r\nwhere to_char(fiscal_date,'DY') in ('SAT','SUN')"
        },
        {
          "name": "Custom SQL Query2",
          "type": "text",
          "sql_query": "select CASE OBJ_SMF_TABLES WHEN 'cmstatsweeklydb_wafl_count' THEN 'CMS Stats wafl Count'\r\nWHEN 'cmstatsweeklydb_wafl_sys' THEN 'CMS Stats wafl Sys'\r\nWHEN 'cmstatsweeklydb_volume_count' THEN 'CMS Stats Volume Count'\r\nWHEN 'cmstatsweeklydb_volume_sys' THEN 'CMS Stats Volume Sys'\r\nWHEN 'Snaplock_volume' THEN 'Snaplock Volume'\r\nWHEN 'Igroup' THEN 'igroup'\r\nWHEN 'Snapmirror_policy' THEN 'snapmirror policy'\r\nWHEN 'Snapmirror_destination' THEN 'SnapMirror Destination' \r\nWHEN 'volume' THEN 'SMFDBV2 Volume'\r\nWhen 'volume_move_show_table' THEN 'Volume Move Show'\r\nELSE OBJ_SMF_TABLES END AS OBJ_SMF_TABLES,AVG_DATA,Max_data\r\n from dlh_reporting_s3.asuprep.PUAT_dashboard_avg_table"
        }
      ]
    },
    {
      "class": "federated",
      "server": null,
      "database": null,
      "schema": null,
      "username": null,
      "port": null,
      "authentication": null,
      "table_name": "Custom SQL Query2",
      "sql_queries": []
    },
    {
      "class": "federated",
      "server": null,
      "database": null,
      "schema": null,
      "username": null,
      "port": null,
      "authentication": null,
      "table_name": "Custom SQL Query2",
      "sql_queries": [
        {
          "name": "Custom SQL Query",
          "type": "text",
          "sql_query": "select 'System' Tab_module,asup_month as asup_date,dt,count(*) as serial_count from\n(select 'System' PUAT_Module,substring(a.asup_id,1,8) as asup_month,a.dt,sys_serial_no from dlh_nsec.objdb.\"system\" a \njoin dlh_nsec.objdb.asup b on a.asup_id = b.asup_id \nwhere a.dt >>= '20240301' and a.dt <<= '20240530'\nand b.dt >>= '20240301' and b.dt <<= '20240530'\nand lower(b.asup_subject) like '%weekly%'\nand upper(b.asup_type) = 'DOT-REGULAR'\nand a.asup_id='2022050100000239'\nand upper(cfo_node_state) not in ('TAKEOVER','DOWN'))\ngroup by asup_month,dt"
        },
        {
          "name": "Custom SQL Query1",
          "type": "text",
          "sql_query": "select fd.*,to_char(fiscal_date,'yyyymmdd') as ft from fiscaltime fd"
        },
        {
          "name": "Custom SQL Query2",
          "type": "text",
          "sql_query": "select CASE OBJ_SMF_TABLES WHEN 'cmstatsweeklydb_wafl_count' THEN 'CMS Stats wafl Count'\r\nWHEN 'cmstatsweeklydb_wafl_sys' THEN 'CMS Stats wafl Sys'\r\nWHEN 'cmstatsweeklydb_volume_count' THEN 'CMS Stats Volume Count'\r\nWHEN 'cmstatsweeklydb_volume_sys' THEN 'CMS Stats Volume Sys'\r\nWHEN 'Snaplock_volume' THEN 'Snaplock Volume'\r\nWHEN 'Igroup' THEN 'igroup'\r\nWHEN 'Snapmirror_policy' THEN 'snapmirror policy'\r\nWHEN 'Snapmirror_destination' THEN 'SnapMirror Destination' \r\nWHEN 'Volume' THEN 'SMFDBV2 Volume'\r\nELSE OBJ_SMF_TABLES END AS OBJ_SMF_TABLES,AVG_DATA\r\n from dlh_reporting_s3.asuprep.puat_avg_table_counts"
        },
        {
          "name": "Custom SQL Query",
          "type": "text",
          "sql_query": "select 'System' Tab_module,asup_month as asup_date,dt,count(*) as serial_count from\n(select 'System' PUAT_Module,substring(a.asup_id,1,8) as asup_month,a.dt,sys_serial_no from dlh_nsec.objdb.\"system\" a \njoin dlh_nsec.objdb.asup b on a.asup_id = b.asup_id \nwhere a.dt >>= '20240301' and a.dt <<= '20240530'\nand b.dt >>= '20240301' and b.dt <<= '20240530'\nand lower(b.asup_subject) like '%weekly%'\nand upper(b.asup_type) = 'DOT-REGULAR'\nand a.asup_id='2022050100000239'\nand upper(cfo_node_state) not in ('TAKEOVER','DOWN'))\ngroup by asup_month,dt"
        },
        {
          "name": "Custom SQL Query1",
          "type": "text",
          "sql_query": "select fd.*,to_char(fiscal_date,'yyyymmdd') as ft from fiscaltime fd"
        },
        {
          "name": "Custom SQL Query2",
          "type": "text",
          "sql_query": "select CASE OBJ_SMF_TABLES WHEN 'cmstatsweeklydb_wafl_count' THEN 'CMS Stats wafl Count'\r\nWHEN 'cmstatsweeklydb_wafl_sys' THEN 'CMS Stats wafl Sys'\r\nWHEN 'cmstatsweeklydb_volume_count' THEN 'CMS Stats Volume Count'\r\nWHEN 'cmstatsweeklydb_volume_sys' THEN 'CMS Stats Volume Sys'\r\nWHEN 'Snaplock_volume' THEN 'Snaplock Volume'\r\nWHEN 'Igroup' THEN 'igroup'\r\nWHEN 'Snapmirror_policy' THEN 'snapmirror policy'\r\nWHEN 'Snapmirror_destination' THEN 'SnapMirror Destination' \r\nWHEN 'Volume' THEN 'SMFDBV2 Volume'\r\nELSE OBJ_SMF_TABLES END AS OBJ_SMF_TABLES,AVG_DATA\r\n from dlh_reporting_s3.asuprep.puat_avg_table_counts"
        }
      ]
    },
    {
      "class": "federated",
      "server": null,
      "database": null,
      "schema": null,
      "username": null,
      "port": null,
      "authentication": null,
      "table_name": "Custom SQL Query2",
      "sql_queries": [
        {
          "name": "Custom SQL Query",
          "type": "text",
          "sql_query": "select * from dlh_reporting_s3.asuprep.PUAT_dremio_dashboard_table_final\r\nwhere puat_module='hussain'"
        },
        {
          "name": "Custom SQL Query1",
          "type": "text",
          "sql_query": "select fd.*,to_char(fiscal_date,'yyyymmdd') as ft from fiscaltime fd\r\nwhere to_char(fiscal_date,'DY') in ('SAT','SUN')"
        },
        {
          "name": "Custom SQL Query2",
          "type": "text",
          "sql_query": "select CASE OBJ_SMF_TABLES WHEN 'cmstatsweeklydb_wafl_count' THEN 'CMS Stats wafl Count'\r\nWHEN 'cmstatsweeklydb_wafl_sys' THEN 'CMS Stats wafl Sys'\r\nWHEN 'cmstatsweeklydb_volume_count' THEN 'CMS Stats Volume Count'\r\nWHEN 'cmstatsweeklydb_volume_sys' THEN 'CMS Stats Volume Sys'\r\nWHEN 'Snaplock_volume' THEN 'Snaplock Volume'\r\nWHEN 'Igroup' THEN 'igroup'\r\nWHEN 'Snapmirror_policy' THEN 'snapmirror policy'\r\nWHEN 'Snapmirror_destination' THEN 'SnapMirror Destination' \r\nWHEN 'volume' THEN 'SMFDBV2 Volume'\r\nWhen 'volume_move_show_table' THEN 'Volume Move Show'\r\nELSE OBJ_SMF_TABLES END AS OBJ_SMF_TABLES,AVG_DATA,Max_data\r\n from dlh_reporting_s3.asuprep.PUAT_dashboard_avg_table"
        },
        {
          "name": "Custom SQL Query",
          "type": "text",
          "sql_query": "select * from dlh_reporting_s3.asuprep.PUAT_dremio_dashboard_table_final\r\nwhere puat_module='hussain'"
        },
        {
          "name": "Custom SQL Query1",
          "type": "text",
          "sql_query": "select fd.*,to_char(fiscal_date,'yyyymmdd') as ft from fiscaltime fd\r\nwhere to_char(fiscal_date,'DY') in ('SAT','SUN')"
        },
        {
          "name": "Custom SQL Query2",
          "type": "text",
          "sql_query": "select CASE OBJ_SMF_TABLES WHEN 'cmstatsweeklydb_wafl_count' THEN 'CMS Stats wafl Count'\r\nWHEN 'cmstatsweeklydb_wafl_sys' THEN 'CMS Stats wafl Sys'\r\nWHEN 'cmstatsweeklydb_volume_count' THEN 'CMS Stats Volume Count'\r\nWHEN 'cmstatsweeklydb_volume_sys' THEN 'CMS Stats Volume Sys'\r\nWHEN 'Snaplock_volume' THEN 'Snaplock Volume'\r\nWHEN 'Igroup' THEN 'igroup'\r\nWHEN 'Snapmirror_policy' THEN 'snapmirror policy'\r\nWHEN 'Snapmirror_destination' THEN 'SnapMirror Destination' \r\nWHEN 'volume' THEN 'SMFDBV2 Volume'\r\nWhen 'volume_move_show_table' THEN 'Volume Move Show'\r\nELSE OBJ_SMF_TABLES END AS OBJ_SMF_TABLES,AVG_DATA,Max_data\r\n from dlh_reporting_s3.asuprep.PUAT_dashboard_avg_table"
        }
      ]
    }
  ]
}